opencf/__init__.py
opencf/app.py
opencf/config/logging.py
opencf/converters/__init__.py
opencf/converters/document.py
opencf/converters/markup.py
opencf/converters/pdf.py
opencf/converters/raster.py
opencf/converters/spreadsheet.py
opencf/converters/video.py
opencf/import_script.py
opencf/io_handlers/__init__.py
opencf/io_handlers/aspose.py
opencf/io_handlers/opencv.py
opencf/io_handlers/pandas.py
opencf/io_handlers/pdf2docx.py
opencf/io_handlers/pillow.py
opencf/io_handlers/pymupdf.py
opencf/io_handlers/pypdf.py
opencf/io_handlers/spreadsheet.py
opencf/py.typed
opencf/utils/image_to_video.py
opencf-0.3.3.dist-info/METADATA
opencf-0.3.3.dist-info/WHEEL
opencf-0.3.3.dist-info/entry_points.txt
opencf-0.3.3.dist-info/RECORD
