Metadata-Version: 2.1
Name: opencf
Version: 0.3.3
Summary: A collection of Python scripts for file conversion tasks, built on top of the opencf-core framework.
Home-page: https://github.com/Hermann-web/opencf
License: MIT
Keywords: file conversion,data processing,file formats
Author: Hermann Agossou
Author-email: agossouhermann7@gmail.com
Maintainer: Hermann Agossou
Maintainer-email: agossouhermann7@gmail.com
Requires-Python: >=3.9,<3.12
Classifier: Development Status :: 4 - Beta
Classifier: Intended Audience :: Developers
Classifier: License :: OSI Approved :: MIT License
Classifier: Programming Language :: Python :: 3
Classifier: Programming Language :: Python :: 3.9
Classifier: Programming Language :: Python :: 3.10
Classifier: Programming Language :: Python :: 3.11
Classifier: Topic :: Software Development :: Libraries :: Python Modules
Provides-Extra: document
Provides-Extra: media
Provides-Extra: pdf
Provides-Extra: tabular
Requires-Dist: aspose-words (>=24.4.0,<25.0.0) ; extra == "document"
Requires-Dist: generalimport (==0.5.2)
Requires-Dist: imageio (>=2.30.0,<3.0.0) ; extra == "media"
Requires-Dist: numpy (>=1.24.0,<2.0.0)
Requires-Dist: opencf-core (>=0.3.3,<0.4.0)
Requires-Dist: opencv-python (>=4.8.1.78,<5.0.0.0) ; extra == "media"
Requires-Dist: openpyxl (>=3.1.3,<4.0.0) ; extra == "tabular"
Requires-Dist: pandas (>=2.0.0,<3.0.0) ; extra == "tabular"
Requires-Dist: pdf2docx (>=0.5.8,<0.6.0) ; extra == "document"
Requires-Dist: pillow (>=10.3.0,<11.0.0)
Requires-Dist: pymupdf (>=1.24.5,<2.0.0) ; extra == "document" or extra == "pdf"
Requires-Dist: pypdf (>=4.2.0,<5.0.0) ; extra == "document" or extra == "pdf"
Requires-Dist: svgtrace (>=2024,<2025) ; extra == "media"
Project-URL: Documentation, https://opencf.readthedocs.io
Project-URL: Repository, https://github.com/Hermann-web/opencf
